aggnf/__init__.py
aggnf/_version.py
aggnf/cli.py
aggnf-0.2.3.dist-info/METADATA
aggnf-0.2.3.dist-info/RECORD
aggnf-0.2.3.dist-info/WHEEL
aggnf-0.2.3.dist-info/entry_points.txt
aggnf-0.2.3.dist-info/top_level.txt
