Metadata-Version: 2.1
Name: aggnf
Version: 0.2.3
Summary: aggnf: Aggregate Nth Field. A small console utility to count/group text data.
Home-page: https://github.com/jwgalley/aggnf
Author: Jesse Galley
Author-email: jesse@jessegalley.net
License: MIT
Platform: UNKNOWN
Classifier: Development Status :: 2 - Pre-Alpha
Classifier: Intended Audience :: Developers
Classifier: License :: OSI Approved :: MIT License
Classifier: Natural Language :: English
Classifier: Programming Language :: Python :: 2
Classifier: Programming Language :: Python :: 2.7
Classifier: Programming Language :: Python :: 3
Classifier: Programming Language :: Python :: 3.3
Classifier: Programming Language :: Python :: 3.4
Classifier: Programming Language :: Python :: 3.5
Requires-Dist: click
Requires-Dist: backport-collections
